inciweb_wildfires/__init__.py
inciweb_wildfires/cli.py
inciweb_wildfires-1.1.1.dist-info/LICENSE
inciweb_wildfires-1.1.1.dist-info/METADATA
inciweb_wildfires-1.1.1.dist-info/WHEEL
inciweb_wildfires-1.1.1.dist-info/entry_points.txt
inciweb_wildfires-1.1.1.dist-info/top_level.txt
inciweb_wildfires-1.1.1.dist-info/RECORD
