Metadata-Version: 2.1
Name: inciweb-wildfires
Version: 1.1.1
Summary: Download wildfire incidents data from InciWeb
Home-page: http://www.github.com/datadesk/inciweb-wildfires
Author: Ben Welsh
Author-email: b@palewi.re
License: MIT
Project-URL: Maintainer, https://github.com/datadesk
Project-URL: Source, https://github.com/datadesk/inciweb-wildfires
Project-URL: Tracker, https://github.com/datadesk/inciweb-wildfires/issues
Classifier: Development Status :: 5 - Production/Stable
Classifier: Programming Language :: Python
Classifier: Programming Language :: Python :: 3.7
Classifier: Programming Language :: Python :: 3.8
Classifier: Programming Language :: Python :: 3.9
Classifier: Programming Language :: Python :: 3.10
Classifier: License :: OSI Approved :: MIT License
License-File: LICENSE
Requires-Dist: requests
Requires-Dist: geojson
Requires-Dist: click
